ff/__init__.py
ff/ff.py
ff/get.py
ff/news.py
ff/test.py
ff/utils.py
ffostrame-0.1.5.data/scripts/ff.py
ffostrame-0.1.5.data/scripts/version.txt
ffostrame-0.1.5.dist-info/LICENSE
ffostrame-0.1.5.dist-info/METADATA
ffostrame-0.1.5.dist-info/WHEEL
ffostrame-0.1.5.dist-info/entry_points.txt
ffostrame-0.1.5.dist-info/top_level.txt
ffostrame-0.1.5.dist-info/RECORD
