Metadata-Version: 2.1
Name: ffostrame
Version: 0.1.5
Summary: A do-it-all Python package for you and me
Home-page: UNKNOWN
Author: Fran Nostrame
Author-email: frank@nostrame.com
License: MIT
Platform: UNKNOWN
Requires-Python: >=3.6.0
Requires-Dist: click (==8.0.0)
Requires-Dist: rich-click (==1.5.1)
Requires-Dist: click-shell (==2.1)
Requires-Dist: whaaaaat (==0.5.2)
Requires-Dist: newsapi-python (==0.2.6)
Requires-Dist: rich (==12.5.1)
Requires-Dist: tabulate (==0.8.10)
Requires-Dist: google-api-core (==2.8.2)
Requires-Dist: google-auth (==2.10.0)
Requires-Dist: google-cloud-secret-manager (==2.12.1)
Requires-Dist: googleapis-common-protos (==1.56.4)
Requires-Dist: google-crc32c (==1.3.0)
